<?xml version="1.0" encoding="utf-8"?>
<root>
  <token>
    <ContextualKind>ClassKeyword</ContextualKind>
    <FullWidth>358</FullWidth>
    <HasAnnotations>False</HasAnnotations>
    <HasDiagnostics>False</HasDiagnostics>
    <HasDirectives>True</HasDirectives>
    <HasLeadingTrivia>True</HasLeadingTrivia>
    <HasStructuredTrivia>True</HasStructuredTrivia>
    <HasTrailingTrivia>True</HasTrailingTrivia>
    <IsBracketed>False</IsBracketed>
    <IsMissing>False</IsMissing>
    <Kind>ClassKeyword</Kind>
    <LeadingWidth>352</LeadingWidth>
    <TrailingWidth>1</TrailingWidth>
    <TypeCharacter>None</TypeCharacter>
    <Value>class</Value>
    <ValueText>class</ValueText>
    <Width>5</Width>
    <LeadingTrivia>
      <trivia>
        <FullWidth>16</FullWidth>
        <HasAnnotations>False</HasAnnotations>
        <HasDiagnostics>False</HasDiagnostics>
        <HasStructure>False</HasStructure>
        <IsDirective>False</IsDirective>
        <IsElastic>False</IsElastic>
        <Kind>CommentTrivia</Kind>
        <Width>16</Width>
        <FullSpan>
          <End>16</End>
          <IsEmpty>False</IsEmpty>
          <Length>16</Length>
          <Start>0</Start>
        </FullSpan>
        <Span>
          <End>16</End>
          <IsEmpty>False</IsEmpty>
          <Length>16</Length>
          <Start>0</Start>
        </Span>
      </trivia>
      <trivia>
        <FullWidth>2</FullWidth>
        <HasAnnotations>False</HasAnnotations>
        <HasDiagnostics>False</HasDiagnostics>
        <HasStructure>False</HasStructure>
        <IsDirective>False</IsDirective>
        <IsElastic>False</IsElastic>
        <Kind>EndOfLineTrivia</Kind>
        <Width>2</Width>
        <FullSpan>
          <End>18</End>
          <IsEmpty>False</IsEmpty>
          <Length>2</Length>
          <Start>16</Start>
        </FullSpan>
        <Span>
          <End>18</End>
          <IsEmpty>False</IsEmpty>
          <Length>2</Length>
          <Start>16</Start>
        </Span>
      </trivia>
      <trivia>
        <FullWidth>16</FullWidth>
        <HasAnnotations>False</HasAnnotations>
        <HasDiagnostics>False</HasDiagnostics>
        <HasStructure>True</HasStructure>
        <IsDirective>True</IsDirective>
        <IsElastic>False</IsElastic>
        <Kind>Directive</Kind>
        <Width>16</Width>
        <FullSpan>
          <End>34</End>
          <IsEmpty>False</IsEmpty>
          <Length>16</Length>
          <Start>18</Start>
        </FullSpan>
        <Span>
          <End>34</End>
          <IsEmpty>False</IsEmpty>
          <Length>16</Length>
          <Start>18</Start>
        </Span>
      </trivia>
      <trivia>
        <FullWidth>138</FullWidth>
        <HasAnnotations>False</HasAnnotations>
        <HasDiagnostics>False</HasDiagnostics>
        <HasStructure>False</HasStructure>
        <IsDirective>False</IsDirective>
        <IsElastic>False</IsElastic>
        <Kind>DisabledTextTrivia</Kind>
        <Width>138</Width>
        <FullSpan>
          <End>172</End>
          <IsEmpty>False</IsEmpty>
          <Length>138</Length>
          <Start>34</Start>
        </FullSpan>
        <Span>
          <End>172</End>
          <IsEmpty>False</IsEmpty>
          <Length>138</Length>
          <Start>34</Start>
        </Span>
      </trivia>
      <trivia>
        <FullWidth>20</FullWidth>
        <HasAnnotations>False</HasAnnotations>
        <HasDiagnostics>False</HasDiagnostics>
        <HasStructure>True</HasStructure>
        <IsDirective>True</IsDirective>
        <IsElastic>False</IsElastic>
        <Kind>Directive</Kind>
        <Width>20</Width>
        <FullSpan>
          <End>192</End>
          <IsEmpty>False</IsEmpty>
          <Length>20</Length>
          <Start>172</Start>
        </FullSpan>
        <Span>
          <End>192</End>
          <IsEmpty>False</IsEmpty>
          <Length>20</Length>
          <Start>172</Start>
        </Span>
      </trivia>
      <trivia>
        <FullWidth>138</FullWidth>
        <HasAnnotations>False</HasAnnotations>
        <HasDiagnostics>False</HasDiagnostics>
        <HasStructure>False</HasStructure>
        <IsDirective>False</IsDirective>
        <IsElastic>False</IsElastic>
        <Kind>DisabledTextTrivia</Kind>
        <Width>138</Width>
        <FullSpan>
          <End>330</End>
          <IsEmpty>False</IsEmpty>
          <Length>138</Length>
          <Start>192</Start>
        </FullSpan>
        <Span>
          <End>330</End>
          <IsEmpty>False</IsEmpty>
          <Length>138</Length>
          <Start>192</Start>
        </Span>
      </trivia>
      <trivia>
        <FullWidth>7</FullWidth>
        <HasAnnotations>False</HasAnnotations>
        <HasDiagnostics>False</HasDiagnostics>
        <HasStructure>True</HasStructure>
        <IsDirective>True</IsDirective>
        <IsElastic>False</IsElastic>
        <Kind>Directive</Kind>
        <Width>7</Width>
        <FullSpan>
          <End>337</End>
          <IsEmpty>False</IsEmpty>
          <Length>7</Length>
          <Start>330</Start>
        </FullSpan>
        <Span>
          <End>337</End>
          <IsEmpty>False</IsEmpty>
          <Length>7</Length>
          <Start>330</Start>
        </Span>
      </trivia>
      <trivia>
        <FullWidth>15</FullWidth>
        <HasAnnotations>False</HasAnnotations>
        <HasDiagnostics>False</HasDiagnostics>
        <HasStructure>True</HasStructure>
        <IsDirective>True</IsDirective>
        <IsElastic>False</IsElastic>
        <Kind>Directive</Kind>
        <Width>15</Width>
        <FullSpan>
          <End>352</End>
          <IsEmpty>False</IsEmpty>
          <Length>15</Length>
          <Start>337</Start>
        </FullSpan>
        <Span>
          <End>352</End>
          <IsEmpty>False</IsEmpty>
          <Length>15</Length>
          <Start>337</Start>
        </Span>
      </trivia>
    </LeadingTrivia>
    <TrailingTrivia>
      <trivia>
        <FullWidth>1</FullWidth>
        <HasAnnotations>False</HasAnnotations>
        <HasDiagnostics>False</HasDiagnostics>
        <HasStructure>False</HasStructure>
        <IsDirective>False</IsDirective>
        <IsElastic>False</IsElastic>
        <Kind>WhitespaceTrivia</Kind>
        <Width>1</Width>
        <FullSpan>
          <End>358</End>
          <IsEmpty>False</IsEmpty>
          <Length>1</Length>
          <Start>357</Start>
        </FullSpan>
        <Span>
          <End>358</End>
          <IsEmpty>False</IsEmpty>
          <Length>1</Length>
          <Start>357</Start>
        </Span>
      </trivia>
    </TrailingTrivia>
    <FullSpan>
      <End>358</End>
      <IsEmpty>False</IsEmpty>
      <Length>358</Length>
      <Start>0</Start>
    </FullSpan>
    <Span>
      <End>357</End>
      <IsEmpty>False</IsEmpty>
      <Length>5</Length>
      <Start>352</Start>
    </Span>
  </token>
  <token>
    <ContextualKind>IdentifierToken</ContextualKind>
    <FullWidth>17</FullWidth>
    <HasAnnotations>False</HasAnnotations>
    <HasDiagnostics>False</HasDiagnostics>
    <HasDirectives>False</HasDirectives>
    <HasLeadingTrivia>False</HasLeadingTrivia>
    <HasStructuredTrivia>False</HasStructuredTrivia>
    <HasTrailingTrivia>False</HasTrailingTrivia>
    <IsBracketed>False</IsBracketed>
    <IsMissing>False</IsMissing>
    <Kind>IdentifierToken</Kind>
    <LeadingWidth>0</LeadingWidth>
    <TrailingWidth>0</TrailingWidth>
    <TypeCharacter>None</TypeCharacter>
    <Value>ConditionalIf2__5</Value>
    <ValueText>ConditionalIf2__5</ValueText>
    <Width>17</Width>
    <LeadingTrivia />
    <TrailingTrivia />
    <FullSpan>
      <End>375</End>
      <IsEmpty>False</IsEmpty>
      <Length>17</Length>
      <Start>358</Start>
    </FullSpan>
    <Span>
      <End>375</End>
      <IsEmpty>False</IsEmpty>
      <Length>17</Length>
      <Start>358</Start>
    </Span>
  </token>
  <token>
    <ContextualKind>StatementTerminatorToken</ContextualKind>
    <FullWidth>2</FullWidth>
    <HasAnnotations>False</HasAnnotations>
    <HasDiagnostics>False</HasDiagnostics>
    <HasDirectives>False</HasDirectives>
    <HasLeadingTrivia>False</HasLeadingTrivia>
    <HasStructuredTrivia>False</HasStructuredTrivia>
    <HasTrailingTrivia>False</HasTrailingTrivia>
    <IsBracketed>False</IsBracketed>
    <IsMissing>False</IsMissing>
    <Kind>StatementTerminatorToken</Kind>
    <LeadingWidth>0</LeadingWidth>
    <TrailingWidth>0</TrailingWidth>
    <TypeCharacter>None</TypeCharacter>
    <Value>
</Value>
    <ValueText>[CR][LF]</ValueText>
    <Width>2</Width>
    <LeadingTrivia />
    <TrailingTrivia />
    <FullSpan>
      <End>377</End>
      <IsEmpty>False</IsEmpty>
      <Length>2</Length>
      <Start>375</Start>
    </FullSpan>
    <Span>
      <End>377</End>
      <IsEmpty>False</IsEmpty>
      <Length>2</Length>
      <Start>375</Start>
    </Span>
  </token>
  <token>
    <ContextualKind>EndKeyword</ContextualKind>
    <FullWidth>4</FullWidth>
    <HasAnnotations>False</HasAnnotations>
    <HasDiagnostics>False</HasDiagnostics>
    <HasDirectives>False</HasDirectives>
    <HasLeadingTrivia>False</HasLeadingTrivia>
    <HasStructuredTrivia>False</HasStructuredTrivia>
    <HasTrailingTrivia>True</HasTrailingTrivia>
    <IsBracketed>False</IsBracketed>
    <IsMissing>False</IsMissing>
    <Kind>EndKeyword</Kind>
    <LeadingWidth>0</LeadingWidth>
    <TrailingWidth>1</TrailingWidth>
    <TypeCharacter>None</TypeCharacter>
    <Value>end</Value>
    <ValueText>end</ValueText>
    <Width>3</Width>
    <LeadingTrivia />
    <TrailingTrivia>
      <trivia>
        <FullWidth>1</FullWidth>
        <HasAnnotations>False</HasAnnotations>
        <HasDiagnostics>False</HasDiagnostics>
        <HasStructure>False</HasStructure>
        <IsDirective>False</IsDirective>
        <IsElastic>False</IsElastic>
        <Kind>WhitespaceTrivia</Kind>
        <Width>1</Width>
        <FullSpan>
          <End>381</End>
          <IsEmpty>False</IsEmpty>
          <Length>1</Length>
          <Start>380</Start>
        </FullSpan>
        <Span>
          <End>381</End>
          <IsEmpty>False</IsEmpty>
          <Length>1</Length>
          <Start>380</Start>
        </Span>
      </trivia>
    </TrailingTrivia>
    <FullSpan>
      <End>381</End>
      <IsEmpty>False</IsEmpty>
      <Length>4</Length>
      <Start>377</Start>
    </FullSpan>
    <Span>
      <End>380</End>
      <IsEmpty>False</IsEmpty>
      <Length>3</Length>
      <Start>377</Start>
    </Span>
  </token>
  <token>
    <ContextualKind>ClassKeyword</ContextualKind>
    <FullWidth>5</FullWidth>
    <HasAnnotations>False</HasAnnotations>
    <HasDiagnostics>False</HasDiagnostics>
    <HasDirectives>False</HasDirectives>
    <HasLeadingTrivia>False</HasLeadingTrivia>
    <HasStructuredTrivia>False</HasStructuredTrivia>
    <HasTrailingTrivia>False</HasTrailingTrivia>
    <IsBracketed>False</IsBracketed>
    <IsMissing>False</IsMissing>
    <Kind>ClassKeyword</Kind>
    <LeadingWidth>0</LeadingWidth>
    <TrailingWidth>0</TrailingWidth>
    <TypeCharacter>None</TypeCharacter>
    <Value>class</Value>
    <ValueText>class</ValueText>
    <Width>5</Width>
    <LeadingTrivia />
    <TrailingTrivia />
    <FullSpan>
      <End>386</End>
      <IsEmpty>False</IsEmpty>
      <Length>5</Length>
      <Start>381</Start>
    </FullSpan>
    <Span>
      <End>386</End>
      <IsEmpty>False</IsEmpty>
      <Length>5</Length>
      <Start>381</Start>
    </Span>
  </token>
  <token>
    <ContextualKind>StatementTerminatorToken</ContextualKind>
    <FullWidth>2</FullWidth>
    <HasAnnotations>False</HasAnnotations>
    <HasDiagnostics>False</HasDiagnostics>
    <HasDirectives>False</HasDirectives>
    <HasLeadingTrivia>False</HasLeadingTrivia>
    <HasStructuredTrivia>False</HasStructuredTrivia>
    <HasTrailingTrivia>False</HasTrailingTrivia>
    <IsBracketed>False</IsBracketed>
    <IsMissing>False</IsMissing>
    <Kind>StatementTerminatorToken</Kind>
    <LeadingWidth>0</LeadingWidth>
    <TrailingWidth>0</TrailingWidth>
    <TypeCharacter>None</TypeCharacter>
    <Value>
</Value>
    <ValueText>[CR][LF]</ValueText>
    <Width>2</Width>
    <LeadingTrivia />
    <TrailingTrivia />
    <FullSpan>
      <End>388</End>
      <IsEmpty>False</IsEmpty>
      <Length>2</Length>
      <Start>386</Start>
    </FullSpan>
    <Span>
      <End>388</End>
      <IsEmpty>False</IsEmpty>
      <Length>2</Length>
      <Start>386</Start>
    </Span>
  </token>
  <token>
    <ContextualKind>ClassKeyword</ContextualKind>
    <FullWidth>58</FullWidth>
    <HasAnnotations>False</HasAnnotations>
    <HasDiagnostics>False</HasDiagnostics>
    <HasDirectives>True</HasDirectives>
    <HasLeadingTrivia>True</HasLeadingTrivia>
    <HasStructuredTrivia>True</HasStructuredTrivia>
    <HasTrailingTrivia>True</HasTrailingTrivia>
    <IsBracketed>False</IsBracketed>
    <IsMissing>False</IsMissing>
    <Kind>ClassKeyword</Kind>
    <LeadingWidth>52</LeadingWidth>
    <TrailingWidth>1</TrailingWidth>
    <TypeCharacter>None</TypeCharacter>
    <Value>Class</Value>
    <ValueText>Class</ValueText>
    <Width>5</Width>
    <LeadingTrivia>
      <trivia>
        <FullWidth>7</FullWidth>
        <HasAnnotations>False</HasAnnotations>
        <HasDiagnostics>False</HasDiagnostics>
        <HasStructure>True</HasStructure>
        <IsDirective>True</IsDirective>
        <IsElastic>False</IsElastic>
        <Kind>Directive</Kind>
        <Width>7</Width>
        <FullSpan>
          <End>395</End>
          <IsEmpty>False</IsEmpty>
          <Length>7</Length>
          <Start>388</Start>
        </FullSpan>
        <Span>
          <End>395</End>
          <IsEmpty>False</IsEmpty>
          <Length>7</Length>
          <Start>388</Start>
        </Span>
      </trivia>
      <trivia>
        <FullWidth>36</FullWidth>
        <HasAnnotations>False</HasAnnotations>
        <HasDiagnostics>False</HasDiagnostics>
        <HasStructure>False</HasStructure>
        <IsDirective>False</IsDirective>
        <IsElastic>False</IsElastic>
        <Kind>DisabledTextTrivia</Kind>
        <Width>36</Width>
        <FullSpan>
          <End>431</End>
          <IsEmpty>False</IsEmpty>
          <Length>36</Length>
          <Start>395</Start>
        </FullSpan>
        <Span>
          <End>431</End>
          <IsEmpty>False</IsEmpty>
          <Length>36</Length>
          <Start>395</Start>
        </Span>
      </trivia>
      <trivia>
        <FullWidth>9</FullWidth>
        <HasAnnotations>False</HasAnnotations>
        <HasDiagnostics>False</HasDiagnostics>
        <HasStructure>True</HasStructure>
        <IsDirective>True</IsDirective>
        <IsElastic>False</IsElastic>
        <Kind>Directive</Kind>
        <Width>9</Width>
        <FullSpan>
          <End>440</End>
          <IsEmpty>False</IsEmpty>
          <Length>9</Length>
          <Start>431</Start>
        </FullSpan>
        <Span>
          <End>440</End>
          <IsEmpty>False</IsEmpty>
          <Length>9</Length>
          <Start>431</Start>
        </Span>
      </trivia>
    </LeadingTrivia>
    <TrailingTrivia>
      <trivia>
        <FullWidth>1</FullWidth>
        <HasAnnotations>False</HasAnnotations>
        <HasDiagnostics>False</HasDiagnostics>
        <HasStructure>False</HasStructure>
        <IsDirective>False</IsDirective>
        <IsElastic>False</IsElastic>
        <Kind>WhitespaceTrivia</Kind>
        <Width>1</Width>
        <FullSpan>
          <End>446</End>
          <IsEmpty>False</IsEmpty>
          <Length>1</Length>
          <Start>445</Start>
        </FullSpan>
        <Span>
          <End>446</End>
          <IsEmpty>False</IsEmpty>
          <Length>1</Length>
          <Start>445</Start>
        </Span>
      </trivia>
    </TrailingTrivia>
    <FullSpan>
      <End>446</End>
      <IsEmpty>False</IsEmpty>
      <Length>58</Length>
      <Start>388</Start>
    </FullSpan>
    <Span>
      <End>445</End>
      <IsEmpty>False</IsEmpty>
      <Length>5</Length>
      <Start>440</Start>
    </Span>
  </token>
  <token>
    <ContextualKind>IdentifierToken</ContextualKind>
    <FullWidth>16</FullWidth>
    <HasAnnotations>False</HasAnnotations>
    <HasDiagnostics>False</HasDiagnostics>
    <HasDirectives>False</HasDirectives>
    <HasLeadingTrivia>False</HasLeadingTrivia>
    <HasStructuredTrivia>False</HasStructuredTrivia>
    <HasTrailingTrivia>False</HasTrailingTrivia>
    <IsBracketed>False</IsBracketed>
    <IsMissing>False</IsMissing>
    <Kind>IdentifierToken</Kind>
    <LeadingWidth>0</LeadingWidth>
    <TrailingWidth>0</TrailingWidth>
    <TypeCharacter>None</TypeCharacter>
    <Value>ConditionalIf2_2</Value>
    <ValueText>ConditionalIf2_2</ValueText>
    <Width>16</Width>
    <LeadingTrivia />
    <TrailingTrivia />
    <FullSpan>
      <End>462</End>
      <IsEmpty>False</IsEmpty>
      <Length>16</Length>
      <Start>446</Start>
    </FullSpan>
    <Span>
      <End>462</End>
      <IsEmpty>False</IsEmpty>
      <Length>16</Length>
      <Start>446</Start>
    </Span>
  </token>
  <token>
    <ContextualKind>StatementTerminatorToken</ContextualKind>
    <FullWidth>2</FullWidth>
    <HasAnnotations>False</HasAnnotations>
    <HasDiagnostics>False</HasDiagnostics>
    <HasDirectives>False</HasDirectives>
    <HasLeadingTrivia>False</HasLeadingTrivia>
    <HasStructuredTrivia>False</HasStructuredTrivia>
    <HasTrailingTrivia>False</HasTrailingTrivia>
    <IsBracketed>False</IsBracketed>
    <IsMissing>False</IsMissing>
    <Kind>StatementTerminatorToken</Kind>
    <LeadingWidth>0</LeadingWidth>
    <TrailingWidth>0</TrailingWidth>
    <TypeCharacter>None</TypeCharacter>
    <Value>
</Value>
    <ValueText>[CR][LF]</ValueText>
    <Width>2</Width>
    <LeadingTrivia />
    <TrailingTrivia />
    <FullSpan>
      <End>464</End>
      <IsEmpty>False</IsEmpty>
      <Length>2</Length>
      <Start>462</Start>
    </FullSpan>
    <Span>
      <End>464</End>
      <IsEmpty>False</IsEmpty>
      <Length>2</Length>
      <Start>462</Start>
    </Span>
  </token>
  <token>
    <ContextualKind>EndKeyword</ContextualKind>
    <FullWidth>4</FullWidth>
    <HasAnnotations>False</HasAnnotations>
    <HasDiagnostics>False</HasDiagnostics>
    <HasDirectives>False</HasDirectives>
    <HasLeadingTrivia>False</HasLeadingTrivia>
    <HasStructuredTrivia>False</HasStructuredTrivia>
    <HasTrailingTrivia>True</HasTrailingTrivia>
    <IsBracketed>False</IsBracketed>
    <IsMissing>False</IsMissing>
    <Kind>EndKeyword</Kind>
    <LeadingWidth>0</LeadingWidth>
    <TrailingWidth>1</TrailingWidth>
    <TypeCharacter>None</TypeCharacter>
    <Value>End</Value>
    <ValueText>End</ValueText>
    <Width>3</Width>
    <LeadingTrivia />
    <TrailingTrivia>
      <trivia>
        <FullWidth>1</FullWidth>
        <HasAnnotations>False</HasAnnotations>
        <HasDiagnostics>False</HasDiagnostics>
        <HasStructure>False</HasStructure>
        <IsDirective>False</IsDirective>
        <IsElastic>False</IsElastic>
        <Kind>WhitespaceTrivia</Kind>
        <Width>1</Width>
        <FullSpan>
          <End>468</End>
          <IsEmpty>False</IsEmpty>
          <Length>1</Length>
          <Start>467</Start>
        </FullSpan>
        <Span>
          <End>468</End>
          <IsEmpty>False</IsEmpty>
          <Length>1</Length>
          <Start>467</Start>
        </Span>
      </trivia>
    </TrailingTrivia>
    <FullSpan>
      <End>468</End>
      <IsEmpty>False</IsEmpty>
      <Length>4</Length>
      <Start>464</Start>
    </FullSpan>
    <Span>
      <End>467</End>
      <IsEmpty>False</IsEmpty>
      <Length>3</Length>
      <Start>464</Start>
    </Span>
  </token>
  <token>
    <ContextualKind>ClassKeyword</ContextualKind>
    <FullWidth>5</FullWidth>
    <HasAnnotations>False</HasAnnotations>
    <HasDiagnostics>False</HasDiagnostics>
    <HasDirectives>False</HasDirectives>
    <HasLeadingTrivia>False</HasLeadingTrivia>
    <HasStructuredTrivia>False</HasStructuredTrivia>
    <HasTrailingTrivia>False</HasTrailingTrivia>
    <IsBracketed>False</IsBracketed>
    <IsMissing>False</IsMissing>
    <Kind>ClassKeyword</Kind>
    <LeadingWidth>0</LeadingWidth>
    <TrailingWidth>0</TrailingWidth>
    <TypeCharacter>None</TypeCharacter>
    <Value>Class</Value>
    <ValueText>Class</ValueText>
    <Width>5</Width>
    <LeadingTrivia />
    <TrailingTrivia />
    <FullSpan>
      <End>473</End>
      <IsEmpty>False</IsEmpty>
      <Length>5</Length>
      <Start>468</Start>
    </FullSpan>
    <Span>
      <End>473</End>
      <IsEmpty>False</IsEmpty>
      <Length>5</Length>
      <Start>468</Start>
    </Span>
  </token>
  <token>
    <ContextualKind>StatementTerminatorToken</ContextualKind>
    <FullWidth>2</FullWidth>
    <HasAnnotations>False</HasAnnotations>
    <HasDiagnostics>False</HasDiagnostics>
    <HasDirectives>False</HasDirectives>
    <HasLeadingTrivia>False</HasLeadingTrivia>
    <HasStructuredTrivia>False</HasStructuredTrivia>
    <HasTrailingTrivia>False</HasTrailingTrivia>
    <IsBracketed>False</IsBracketed>
    <IsMissing>False</IsMissing>
    <Kind>StatementTerminatorToken</Kind>
    <LeadingWidth>0</LeadingWidth>
    <TrailingWidth>0</TrailingWidth>
    <TypeCharacter>None</TypeCharacter>
    <Value>
</Value>
    <ValueText>[CR][LF]</ValueText>
    <Width>2</Width>
    <LeadingTrivia />
    <TrailingTrivia />
    <FullSpan>
      <End>475</End>
      <IsEmpty>False</IsEmpty>
      <Length>2</Length>
      <Start>473</Start>
    </FullSpan>
    <Span>
      <End>475</End>
      <IsEmpty>False</IsEmpty>
      <Length>2</Length>
      <Start>473</Start>
    </Span>
  </token>
  <token>
    <ContextualKind>EndOfFileToken</ContextualKind>
    <FullWidth>7</FullWidth>
    <HasAnnotations>False</HasAnnotations>
    <HasDiagnostics>False</HasDiagnostics>
    <HasDirectives>True</HasDirectives>
    <HasLeadingTrivia>True</HasLeadingTrivia>
    <HasStructuredTrivia>True</HasStructuredTrivia>
    <HasTrailingTrivia>False</HasTrailingTrivia>
    <IsBracketed>False</IsBracketed>
    <IsMissing>False</IsMissing>
    <Kind>EndOfFileToken</Kind>
    <LeadingWidth>7</LeadingWidth>
    <TrailingWidth>0</TrailingWidth>
    <TypeCharacter>None</TypeCharacter>
    <Value />
    <ValueText />
    <Width>0</Width>
    <LeadingTrivia>
      <trivia>
        <FullWidth>7</FullWidth>
        <HasAnnotations>False</HasAnnotations>
        <HasDiagnostics>False</HasDiagnostics>
        <HasStructure>True</HasStructure>
        <IsDirective>True</IsDirective>
        <IsElastic>False</IsElastic>
        <Kind>Directive</Kind>
        <Width>7</Width>
        <FullSpan>
          <End>482</End>
          <IsEmpty>False</IsEmpty>
          <Length>7</Length>
          <Start>475</Start>
        </FullSpan>
        <Span>
          <End>482</End>
          <IsEmpty>False</IsEmpty>
          <Length>7</Length>
          <Start>475</Start>
        </Span>
      </trivia>
    </LeadingTrivia>
    <TrailingTrivia />
    <FullSpan>
      <End>482</End>
      <IsEmpty>False</IsEmpty>
      <Length>7</Length>
      <Start>475</Start>
    </FullSpan>
    <Span>
      <End>482</End>
      <IsEmpty>True</IsEmpty>
      <Length>0</Length>
      <Start>482</Start>
    </Span>
  </token>
</root>