<?xml version="1.0" encoding="utf-8"?>
<root>
  <token>
    <ContextualKind>ClassKeyword</ContextualKind>
    <FullWidth>6</FullWidth>
    <HasAnnotations>False</HasAnnotations>
    <HasDiagnostics>False</HasDiagnostics>
    <HasDirectives>False</HasDirectives>
    <HasLeadingTrivia>False</HasLeadingTrivia>
    <HasStructuredTrivia>False</HasStructuredTrivia>
    <HasTrailingTrivia>True</HasTrailingTrivia>
    <IsBracketed>False</IsBracketed>
    <IsMissing>False</IsMissing>
    <Kind>ClassKeyword</Kind>
    <LeadingWidth>0</LeadingWidth>
    <TrailingWidth>1</TrailingWidth>
    <TypeCharacter>None</TypeCharacter>
    <Value>class</Value>
    <ValueText>class</ValueText>
    <Width>5</Width>
    <LeadingTrivia />
    <TrailingTrivia>
      <trivia>
        <FullWidth>1</FullWidth>
        <HasAnnotations>False</HasAnnotations>
        <HasDiagnostics>False</HasDiagnostics>
        <HasStructure>False</HasStructure>
        <IsDirective>False</IsDirective>
        <IsElastic>False</IsElastic>
        <Kind>WhitespaceTrivia</Kind>
        <Width>1</Width>
        <FullSpan>
          <End>6</End>
          <IsEmpty>False</IsEmpty>
          <Length>1</Length>
          <Start>5</Start>
        </FullSpan>
        <Span>
          <End>6</End>
          <IsEmpty>False</IsEmpty>
          <Length>1</Length>
          <Start>5</Start>
        </Span>
      </trivia>
    </TrailingTrivia>
    <FullSpan>
      <End>6</End>
      <IsEmpty>False</IsEmpty>
      <Length>6</Length>
      <Start>0</Start>
    </FullSpan>
    <Span>
      <End>5</End>
      <IsEmpty>False</IsEmpty>
      <Length>5</Length>
      <Start>0</Start>
    </Span>
  </token>
  <token>
    <ContextualKind>IdentifierToken</ContextualKind>
    <FullWidth>30</FullWidth>
    <HasAnnotations>False</HasAnnotations>
    <HasDiagnostics>False</HasDiagnostics>
    <HasDirectives>False</HasDirectives>
    <HasLeadingTrivia>False</HasLeadingTrivia>
    <HasStructuredTrivia>False</HasStructuredTrivia>
    <HasTrailingTrivia>True</HasTrailingTrivia>
    <IsBracketed>False</IsBracketed>
    <IsMissing>False</IsMissing>
    <Kind>IdentifierToken</Kind>
    <LeadingWidth>0</LeadingWidth>
    <TrailingWidth>2</TrailingWidth>
    <TypeCharacter>None</TypeCharacter>
    <Value>NotEqualsConstantExpression1</Value>
    <ValueText>NotEqualsConstantExpression1</ValueText>
    <Width>28</Width>
    <LeadingTrivia />
    <TrailingTrivia>
      <trivia>
        <FullWidth>2</FullWidth>
        <HasAnnotations>False</HasAnnotations>
        <HasDiagnostics>False</HasDiagnostics>
        <HasStructure>False</HasStructure>
        <IsDirective>False</IsDirective>
        <IsElastic>False</IsElastic>
        <Kind>WhitespaceTrivia</Kind>
        <Width>2</Width>
        <FullSpan>
          <End>36</End>
          <IsEmpty>False</IsEmpty>
          <Length>2</Length>
          <Start>34</Start>
        </FullSpan>
        <Span>
          <End>36</End>
          <IsEmpty>False</IsEmpty>
          <Length>2</Length>
          <Start>34</Start>
        </Span>
      </trivia>
    </TrailingTrivia>
    <FullSpan>
      <End>36</End>
      <IsEmpty>False</IsEmpty>
      <Length>30</Length>
      <Start>6</Start>
    </FullSpan>
    <Span>
      <End>34</End>
      <IsEmpty>False</IsEmpty>
      <Length>28</Length>
      <Start>6</Start>
    </Span>
  </token>
  <token>
    <ContextualKind>StatementTerminatorToken</ContextualKind>
    <FullWidth>2</FullWidth>
    <HasAnnotations>False</HasAnnotations>
    <HasDiagnostics>False</HasDiagnostics>
    <HasDirectives>False</HasDirectives>
    <HasLeadingTrivia>False</HasLeadingTrivia>
    <HasStructuredTrivia>False</HasStructuredTrivia>
    <HasTrailingTrivia>False</HasTrailingTrivia>
    <IsBracketed>False</IsBracketed>
    <IsMissing>False</IsMissing>
    <Kind>StatementTerminatorToken</Kind>
    <LeadingWidth>0</LeadingWidth>
    <TrailingWidth>0</TrailingWidth>
    <TypeCharacter>None</TypeCharacter>
    <Value>
</Value>
    <ValueText>[CR][LF]</ValueText>
    <Width>2</Width>
    <LeadingTrivia />
    <TrailingTrivia />
    <FullSpan>
      <End>38</End>
      <IsEmpty>False</IsEmpty>
      <Length>2</Length>
      <Start>36</Start>
    </FullSpan>
    <Span>
      <End>38</End>
      <IsEmpty>False</IsEmpty>
      <Length>2</Length>
      <Start>36</Start>
    </Span>
  </token>
  <token>
    <ContextualKind>ConstKeyword</ContextualKind>
    <FullWidth>7</FullWidth>
    <HasAnnotations>False</HasAnnotations>
    <HasDiagnostics>False</HasDiagnostics>
    <HasDirectives>False</HasDirectives>
    <HasLeadingTrivia>True</HasLeadingTrivia>
    <HasStructuredTrivia>False</HasStructuredTrivia>
    <HasTrailingTrivia>True</HasTrailingTrivia>
    <IsBracketed>False</IsBracketed>
    <IsMissing>False</IsMissing>
    <Kind>ConstKeyword</Kind>
    <LeadingWidth>1</LeadingWidth>
    <TrailingWidth>1</TrailingWidth>
    <TypeCharacter>None</TypeCharacter>
    <Value>Const</Value>
    <ValueText>Const</ValueText>
    <Width>5</Width>
    <LeadingTrivia>
      <trivia>
        <FullWidth>1</FullWidth>
        <HasAnnotations>False</HasAnnotations>
        <HasDiagnostics>False</HasDiagnostics>
        <HasStructure>False</HasStructure>
        <IsDirective>False</IsDirective>
        <IsElastic>False</IsElastic>
        <Kind>WhitespaceTrivia</Kind>
        <Width>1</Width>
        <FullSpan>
          <End>39</End>
          <IsEmpty>False</IsEmpty>
          <Length>1</Length>
          <Start>38</Start>
        </FullSpan>
        <Span>
          <End>39</End>
          <IsEmpty>False</IsEmpty>
          <Length>1</Length>
          <Start>38</Start>
        </Span>
      </trivia>
    </LeadingTrivia>
    <TrailingTrivia>
      <trivia>
        <FullWidth>1</FullWidth>
        <HasAnnotations>False</HasAnnotations>
        <HasDiagnostics>False</HasDiagnostics>
        <HasStructure>False</HasStructure>
        <IsDirective>False</IsDirective>
        <IsElastic>False</IsElastic>
        <Kind>WhitespaceTrivia</Kind>
        <Width>1</Width>
        <FullSpan>
          <End>45</End>
          <IsEmpty>False</IsEmpty>
          <Length>1</Length>
          <Start>44</Start>
        </FullSpan>
        <Span>
          <End>45</End>
          <IsEmpty>False</IsEmpty>
          <Length>1</Length>
          <Start>44</Start>
        </Span>
      </trivia>
    </TrailingTrivia>
    <FullSpan>
      <End>45</End>
      <IsEmpty>False</IsEmpty>
      <Length>7</Length>
      <Start>38</Start>
    </FullSpan>
    <Span>
      <End>44</End>
      <IsEmpty>False</IsEmpty>
      <Length>5</Length>
      <Start>39</Start>
    </Span>
  </token>
  <token>
    <ContextualKind>IdentifierToken</ContextualKind>
    <FullWidth>7</FullWidth>
    <HasAnnotations>False</HasAnnotations>
    <HasDiagnostics>False</HasDiagnostics>
    <HasDirectives>False</HasDirectives>
    <HasLeadingTrivia>False</HasLeadingTrivia>
    <HasStructuredTrivia>False</HasStructuredTrivia>
    <HasTrailingTrivia>True</HasTrailingTrivia>
    <IsBracketed>False</IsBracketed>
    <IsMissing>False</IsMissing>
    <Kind>IdentifierToken</Kind>
    <LeadingWidth>0</LeadingWidth>
    <TrailingWidth>1</TrailingWidth>
    <TypeCharacter>None</TypeCharacter>
    <Value>const1</Value>
    <ValueText>const1</ValueText>
    <Width>6</Width>
    <LeadingTrivia />
    <TrailingTrivia>
      <trivia>
        <FullWidth>1</FullWidth>
        <HasAnnotations>False</HasAnnotations>
        <HasDiagnostics>False</HasDiagnostics>
        <HasStructure>False</HasStructure>
        <IsDirective>False</IsDirective>
        <IsElastic>False</IsElastic>
        <Kind>WhitespaceTrivia</Kind>
        <Width>1</Width>
        <FullSpan>
          <End>52</End>
          <IsEmpty>False</IsEmpty>
          <Length>1</Length>
          <Start>51</Start>
        </FullSpan>
        <Span>
          <End>52</End>
          <IsEmpty>False</IsEmpty>
          <Length>1</Length>
          <Start>51</Start>
        </Span>
      </trivia>
    </TrailingTrivia>
    <FullSpan>
      <End>52</End>
      <IsEmpty>False</IsEmpty>
      <Length>7</Length>
      <Start>45</Start>
    </FullSpan>
    <Span>
      <End>51</End>
      <IsEmpty>False</IsEmpty>
      <Length>6</Length>
      <Start>45</Start>
    </Span>
  </token>
  <token>
    <ContextualKind>AsKeyword</ContextualKind>
    <FullWidth>3</FullWidth>
    <HasAnnotations>False</HasAnnotations>
    <HasDiagnostics>False</HasDiagnostics>
    <HasDirectives>False</HasDirectives>
    <HasLeadingTrivia>False</HasLeadingTrivia>
    <HasStructuredTrivia>False</HasStructuredTrivia>
    <HasTrailingTrivia>True</HasTrailingTrivia>
    <IsBracketed>False</IsBracketed>
    <IsMissing>False</IsMissing>
    <Kind>AsKeyword</Kind>
    <LeadingWidth>0</LeadingWidth>
    <TrailingWidth>1</TrailingWidth>
    <TypeCharacter>None</TypeCharacter>
    <Value>As</Value>
    <ValueText>As</ValueText>
    <Width>2</Width>
    <LeadingTrivia />
    <TrailingTrivia>
      <trivia>
        <FullWidth>1</FullWidth>
        <HasAnnotations>False</HasAnnotations>
        <HasDiagnostics>False</HasDiagnostics>
        <HasStructure>False</HasStructure>
        <IsDirective>False</IsDirective>
        <IsElastic>False</IsElastic>
        <Kind>WhitespaceTrivia</Kind>
        <Width>1</Width>
        <FullSpan>
          <End>55</End>
          <IsEmpty>False</IsEmpty>
          <Length>1</Length>
          <Start>54</Start>
        </FullSpan>
        <Span>
          <End>55</End>
          <IsEmpty>False</IsEmpty>
          <Length>1</Length>
          <Start>54</Start>
        </Span>
      </trivia>
    </TrailingTrivia>
    <FullSpan>
      <End>55</End>
      <IsEmpty>False</IsEmpty>
      <Length>3</Length>
      <Start>52</Start>
    </FullSpan>
    <Span>
      <End>54</End>
      <IsEmpty>False</IsEmpty>
      <Length>2</Length>
      <Start>52</Start>
    </Span>
  </token>
  <token>
    <ContextualKind>BooleanKeyword</ContextualKind>
    <FullWidth>8</FullWidth>
    <HasAnnotations>False</HasAnnotations>
    <HasDiagnostics>False</HasDiagnostics>
    <HasDirectives>False</HasDirectives>
    <HasLeadingTrivia>False</HasLeadingTrivia>
    <HasStructuredTrivia>False</HasStructuredTrivia>
    <HasTrailingTrivia>True</HasTrailingTrivia>
    <IsBracketed>False</IsBracketed>
    <IsMissing>False</IsMissing>
    <Kind>BooleanKeyword</Kind>
    <LeadingWidth>0</LeadingWidth>
    <TrailingWidth>1</TrailingWidth>
    <TypeCharacter>None</TypeCharacter>
    <Value>Boolean</Value>
    <ValueText>Boolean</ValueText>
    <Width>7</Width>
    <LeadingTrivia />
    <TrailingTrivia>
      <trivia>
        <FullWidth>1</FullWidth>
        <HasAnnotations>False</HasAnnotations>
        <HasDiagnostics>False</HasDiagnostics>
        <HasStructure>False</HasStructure>
        <IsDirective>False</IsDirective>
        <IsElastic>False</IsElastic>
        <Kind>WhitespaceTrivia</Kind>
        <Width>1</Width>
        <FullSpan>
          <End>63</End>
          <IsEmpty>False</IsEmpty>
          <Length>1</Length>
          <Start>62</Start>
        </FullSpan>
        <Span>
          <End>63</End>
          <IsEmpty>False</IsEmpty>
          <Length>1</Length>
          <Start>62</Start>
        </Span>
      </trivia>
    </TrailingTrivia>
    <FullSpan>
      <End>63</End>
      <IsEmpty>False</IsEmpty>
      <Length>8</Length>
      <Start>55</Start>
    </FullSpan>
    <Span>
      <End>62</End>
      <IsEmpty>False</IsEmpty>
      <Length>7</Length>
      <Start>55</Start>
    </Span>
  </token>
  <token>
    <ContextualKind>EqualsToken</ContextualKind>
    <FullWidth>2</FullWidth>
    <HasAnnotations>False</HasAnnotations>
    <HasDiagnostics>False</HasDiagnostics>
    <HasDirectives>False</HasDirectives>
    <HasLeadingTrivia>False</HasLeadingTrivia>
    <HasStructuredTrivia>False</HasStructuredTrivia>
    <HasTrailingTrivia>True</HasTrailingTrivia>
    <IsBracketed>False</IsBracketed>
    <IsMissing>False</IsMissing>
    <Kind>EqualsToken</Kind>
    <LeadingWidth>0</LeadingWidth>
    <TrailingWidth>1</TrailingWidth>
    <TypeCharacter>None</TypeCharacter>
    <Value>=</Value>
    <ValueText>=</ValueText>
    <Width>1</Width>
    <LeadingTrivia />
    <TrailingTrivia>
      <trivia>
        <FullWidth>1</FullWidth>
        <HasAnnotations>False</HasAnnotations>
        <HasDiagnostics>False</HasDiagnostics>
        <HasStructure>False</HasStructure>
        <IsDirective>False</IsDirective>
        <IsElastic>False</IsElastic>
        <Kind>WhitespaceTrivia</Kind>
        <Width>1</Width>
        <FullSpan>
          <End>65</End>
          <IsEmpty>False</IsEmpty>
          <Length>1</Length>
          <Start>64</Start>
        </FullSpan>
        <Span>
          <End>65</End>
          <IsEmpty>False</IsEmpty>
          <Length>1</Length>
          <Start>64</Start>
        </Span>
      </trivia>
    </TrailingTrivia>
    <FullSpan>
      <End>65</End>
      <IsEmpty>False</IsEmpty>
      <Length>2</Length>
      <Start>63</Start>
    </FullSpan>
    <Span>
      <End>64</End>
      <IsEmpty>False</IsEmpty>
      <Length>1</Length>
      <Start>63</Start>
    </Span>
  </token>
  <token>
    <ContextualKind>IntegerLiteralToken</ContextualKind>
    <FullWidth>2</FullWidth>
    <HasAnnotations>False</HasAnnotations>
    <HasDiagnostics>False</HasDiagnostics>
    <HasDirectives>False</HasDirectives>
    <HasLeadingTrivia>False</HasLeadingTrivia>
    <HasStructuredTrivia>False</HasStructuredTrivia>
    <HasTrailingTrivia>True</HasTrailingTrivia>
    <IsBracketed>False</IsBracketed>
    <IsMissing>False</IsMissing>
    <Kind>IntegerLiteralToken</Kind>
    <LeadingWidth>0</LeadingWidth>
    <TrailingWidth>1</TrailingWidth>
    <TypeCharacter>None</TypeCharacter>
    <Value>2</Value>
    <ValueText>2</ValueText>
    <Width>1</Width>
    <LeadingTrivia />
    <TrailingTrivia>
      <trivia>
        <FullWidth>1</FullWidth>
        <HasAnnotations>False</HasAnnotations>
        <HasDiagnostics>False</HasDiagnostics>
        <HasStructure>False</HasStructure>
        <IsDirective>False</IsDirective>
        <IsElastic>False</IsElastic>
        <Kind>WhitespaceTrivia</Kind>
        <Width>1</Width>
        <FullSpan>
          <End>67</End>
          <IsEmpty>False</IsEmpty>
          <Length>1</Length>
          <Start>66</Start>
        </FullSpan>
        <Span>
          <End>67</End>
          <IsEmpty>False</IsEmpty>
          <Length>1</Length>
          <Start>66</Start>
        </Span>
      </trivia>
    </TrailingTrivia>
    <FullSpan>
      <End>67</End>
      <IsEmpty>False</IsEmpty>
      <Length>2</Length>
      <Start>65</Start>
    </FullSpan>
    <Span>
      <End>66</End>
      <IsEmpty>False</IsEmpty>
      <Length>1</Length>
      <Start>65</Start>
    </Span>
  </token>
  <token>
    <ContextualKind>LessThanGreaterThanToken</ContextualKind>
    <FullWidth>3</FullWidth>
    <HasAnnotations>False</HasAnnotations>
    <HasDiagnostics>False</HasDiagnostics>
    <HasDirectives>False</HasDirectives>
    <HasLeadingTrivia>False</HasLeadingTrivia>
    <HasStructuredTrivia>False</HasStructuredTrivia>
    <HasTrailingTrivia>True</HasTrailingTrivia>
    <IsBracketed>False</IsBracketed>
    <IsMissing>False</IsMissing>
    <Kind>LessThanGreaterThanToken</Kind>
    <LeadingWidth>0</LeadingWidth>
    <TrailingWidth>1</TrailingWidth>
    <TypeCharacter>None</TypeCharacter>
    <Value>&lt;&gt;</Value>
    <ValueText>&lt;&gt;</ValueText>
    <Width>2</Width>
    <LeadingTrivia />
    <TrailingTrivia>
      <trivia>
        <FullWidth>1</FullWidth>
        <HasAnnotations>False</HasAnnotations>
        <HasDiagnostics>False</HasDiagnostics>
        <HasStructure>False</HasStructure>
        <IsDirective>False</IsDirective>
        <IsElastic>False</IsElastic>
        <Kind>WhitespaceTrivia</Kind>
        <Width>1</Width>
        <FullSpan>
          <End>70</End>
          <IsEmpty>False</IsEmpty>
          <Length>1</Length>
          <Start>69</Start>
        </FullSpan>
        <Span>
          <End>70</End>
          <IsEmpty>False</IsEmpty>
          <Length>1</Length>
          <Start>69</Start>
        </Span>
      </trivia>
    </TrailingTrivia>
    <FullSpan>
      <End>70</End>
      <IsEmpty>False</IsEmpty>
      <Length>3</Length>
      <Start>67</Start>
    </FullSpan>
    <Span>
      <End>69</End>
      <IsEmpty>False</IsEmpty>
      <Length>2</Length>
      <Start>67</Start>
    </Span>
  </token>
  <token>
    <ContextualKind>IntegerLiteralToken</ContextualKind>
    <FullWidth>1</FullWidth>
    <HasAnnotations>False</HasAnnotations>
    <HasDiagnostics>False</HasDiagnostics>
    <HasDirectives>False</HasDirectives>
    <HasLeadingTrivia>False</HasLeadingTrivia>
    <HasStructuredTrivia>False</HasStructuredTrivia>
    <HasTrailingTrivia>False</HasTrailingTrivia>
    <IsBracketed>False</IsBracketed>
    <IsMissing>False</IsMissing>
    <Kind>IntegerLiteralToken</Kind>
    <LeadingWidth>0</LeadingWidth>
    <TrailingWidth>0</TrailingWidth>
    <TypeCharacter>None</TypeCharacter>
    <Value>3</Value>
    <ValueText>3</ValueText>
    <Width>1</Width>
    <LeadingTrivia />
    <TrailingTrivia />
    <FullSpan>
      <End>71</End>
      <IsEmpty>False</IsEmpty>
      <Length>1</Length>
      <Start>70</Start>
    </FullSpan>
    <Span>
      <End>71</End>
      <IsEmpty>False</IsEmpty>
      <Length>1</Length>
      <Start>70</Start>
    </Span>
  </token>
  <token>
    <ContextualKind>StatementTerminatorToken</ContextualKind>
    <FullWidth>2</FullWidth>
    <HasAnnotations>False</HasAnnotations>
    <HasDiagnostics>False</HasDiagnostics>
    <HasDirectives>False</HasDirectives>
    <HasLeadingTrivia>False</HasLeadingTrivia>
    <HasStructuredTrivia>False</HasStructuredTrivia>
    <HasTrailingTrivia>False</HasTrailingTrivia>
    <IsBracketed>False</IsBracketed>
    <IsMissing>False</IsMissing>
    <Kind>StatementTerminatorToken</Kind>
    <LeadingWidth>0</LeadingWidth>
    <TrailingWidth>0</TrailingWidth>
    <TypeCharacter>None</TypeCharacter>
    <Value>
</Value>
    <ValueText>[CR][LF]</ValueText>
    <Width>2</Width>
    <LeadingTrivia />
    <TrailingTrivia />
    <FullSpan>
      <End>73</End>
      <IsEmpty>False</IsEmpty>
      <Length>2</Length>
      <Start>71</Start>
    </FullSpan>
    <Span>
      <End>73</End>
      <IsEmpty>False</IsEmpty>
      <Length>2</Length>
      <Start>71</Start>
    </Span>
  </token>
  <token>
    <ContextualKind>EndKeyword</ContextualKind>
    <FullWidth>4</FullWidth>
    <HasAnnotations>False</HasAnnotations>
    <HasDiagnostics>False</HasDiagnostics>
    <HasDirectives>False</HasDirectives>
    <HasLeadingTrivia>False</HasLeadingTrivia>
    <HasStructuredTrivia>False</HasStructuredTrivia>
    <HasTrailingTrivia>True</HasTrailingTrivia>
    <IsBracketed>False</IsBracketed>
    <IsMissing>False</IsMissing>
    <Kind>EndKeyword</Kind>
    <LeadingWidth>0</LeadingWidth>
    <TrailingWidth>1</TrailingWidth>
    <TypeCharacter>None</TypeCharacter>
    <Value>end</Value>
    <ValueText>end</ValueText>
    <Width>3</Width>
    <LeadingTrivia />
    <TrailingTrivia>
      <trivia>
        <FullWidth>1</FullWidth>
        <HasAnnotations>False</HasAnnotations>
        <HasDiagnostics>False</HasDiagnostics>
        <HasStructure>False</HasStructure>
        <IsDirective>False</IsDirective>
        <IsElastic>False</IsElastic>
        <Kind>WhitespaceTrivia</Kind>
        <Width>1</Width>
        <FullSpan>
          <End>77</End>
          <IsEmpty>False</IsEmpty>
          <Length>1</Length>
          <Start>76</Start>
        </FullSpan>
        <Span>
          <End>77</End>
          <IsEmpty>False</IsEmpty>
          <Length>1</Length>
          <Start>76</Start>
        </Span>
      </trivia>
    </TrailingTrivia>
    <FullSpan>
      <End>77</End>
      <IsEmpty>False</IsEmpty>
      <Length>4</Length>
      <Start>73</Start>
    </FullSpan>
    <Span>
      <End>76</End>
      <IsEmpty>False</IsEmpty>
      <Length>3</Length>
      <Start>73</Start>
    </Span>
  </token>
  <token>
    <ContextualKind>ClassKeyword</ContextualKind>
    <FullWidth>7</FullWidth>
    <HasAnnotations>False</HasAnnotations>
    <HasDiagnostics>False</HasDiagnostics>
    <HasDirectives>False</HasDirectives>
    <HasLeadingTrivia>False</HasLeadingTrivia>
    <HasStructuredTrivia>False</HasStructuredTrivia>
    <HasTrailingTrivia>True</HasTrailingTrivia>
    <IsBracketed>False</IsBracketed>
    <IsMissing>False</IsMissing>
    <Kind>ClassKeyword</Kind>
    <LeadingWidth>0</LeadingWidth>
    <TrailingWidth>2</TrailingWidth>
    <TypeCharacter>None</TypeCharacter>
    <Value>class</Value>
    <ValueText>class</ValueText>
    <Width>5</Width>
    <LeadingTrivia />
    <TrailingTrivia>
      <trivia>
        <FullWidth>2</FullWidth>
        <HasAnnotations>False</HasAnnotations>
        <HasDiagnostics>False</HasDiagnostics>
        <HasStructure>False</HasStructure>
        <IsDirective>False</IsDirective>
        <IsElastic>False</IsElastic>
        <Kind>WhitespaceTrivia</Kind>
        <Width>2</Width>
        <FullSpan>
          <End>84</End>
          <IsEmpty>False</IsEmpty>
          <Length>2</Length>
          <Start>82</Start>
        </FullSpan>
        <Span>
          <End>84</End>
          <IsEmpty>False</IsEmpty>
          <Length>2</Length>
          <Start>82</Start>
        </Span>
      </trivia>
    </TrailingTrivia>
    <FullSpan>
      <End>84</End>
      <IsEmpty>False</IsEmpty>
      <Length>7</Length>
      <Start>77</Start>
    </FullSpan>
    <Span>
      <End>82</End>
      <IsEmpty>False</IsEmpty>
      <Length>5</Length>
      <Start>77</Start>
    </Span>
  </token>
  <token>
    <ContextualKind>StatementTerminatorToken</ContextualKind>
    <FullWidth>2</FullWidth>
    <HasAnnotations>False</HasAnnotations>
    <HasDiagnostics>False</HasDiagnostics>
    <HasDirectives>False</HasDirectives>
    <HasLeadingTrivia>False</HasLeadingTrivia>
    <HasStructuredTrivia>False</HasStructuredTrivia>
    <HasTrailingTrivia>False</HasTrailingTrivia>
    <IsBracketed>False</IsBracketed>
    <IsMissing>False</IsMissing>
    <Kind>StatementTerminatorToken</Kind>
    <LeadingWidth>0</LeadingWidth>
    <TrailingWidth>0</TrailingWidth>
    <TypeCharacter>None</TypeCharacter>
    <Value>
</Value>
    <ValueText>[CR][LF]</ValueText>
    <Width>2</Width>
    <LeadingTrivia />
    <TrailingTrivia />
    <FullSpan>
      <End>86</End>
      <IsEmpty>False</IsEmpty>
      <Length>2</Length>
      <Start>84</Start>
    </FullSpan>
    <Span>
      <End>86</End>
      <IsEmpty>False</IsEmpty>
      <Length>2</Length>
      <Start>84</Start>
    </Span>
  </token>
  <token>
    <ContextualKind>EndOfFileToken</ContextualKind>
    <FullWidth>0</FullWidth>
    <HasAnnotations>False</HasAnnotations>
    <HasDiagnostics>False</HasDiagnostics>
    <HasDirectives>False</HasDirectives>
    <HasLeadingTrivia>False</HasLeadingTrivia>
    <HasStructuredTrivia>False</HasStructuredTrivia>
    <HasTrailingTrivia>False</HasTrailingTrivia>
    <IsBracketed>False</IsBracketed>
    <IsMissing>False</IsMissing>
    <Kind>EndOfFileToken</Kind>
    <LeadingWidth>0</LeadingWidth>
    <TrailingWidth>0</TrailingWidth>
    <TypeCharacter>None</TypeCharacter>
    <Value />
    <ValueText />
    <Width>0</Width>
    <LeadingTrivia />
    <TrailingTrivia />
    <FullSpan>
      <End>86</End>
      <IsEmpty>True</IsEmpty>
      <Length>0</Length>
      <Start>86</Start>
    </FullSpan>
    <Span>
      <End>86</End>
      <IsEmpty>True</IsEmpty>
      <Length>0</Length>
      <Start>86</Start>
    </Span>
  </token>
</root>